[{"nivel": 1.11, "caudal": 25.42, "timestamp": "2026-02-19T02:15:28Z"}, {"nivel": 1.12, "caudal": 25.6, "timestamp": "2026-02-19T02:30:31Z"}, {"nivel": 1.1, "caudal": 24.81, "timestamp": "2026-02-19T02:45:24Z"}, {"nivel": 1.12, "caudal": 25.54, "timestamp": "2026-02-19T03:00:39Z"}, {"nivel": 1.12, "caudal": 25.53, "timestamp": "2026-02-19T03:15:26Z"}, {"nivel": 1.12, "caudal": 25.51, "timestamp": "2026-02-19T03:30:31Z"}, {"nivel": 1.12, "caudal": 25.65, "timestamp": "2026-02-19T03:44:54Z"}, {"nivel": 1.12, "caudal": 25.65, "timestamp": "2026-02-19T03:45:23Z"}, {"nivel": 1.11, "caudal": 25.19, "timestamp": "2026-02-19T04:00:35Z"}, {"nivel": 1.12, "caudal": 25.6, "timestamp": "2026-02-19T04:15:24Z"}, {"nivel": 1.1, "caudal": 24.81, "timestamp": "2026-02-19T04:30:32Z"}, {"nivel": 1.12, "caudal": 25.64, "timestamp": "2026-02-19T04:45:24Z"}, {"nivel": 1.11, "caudal": 25.05, "timestamp": "2026-02-19T05:00:39Z"}, {"nivel": 1.11, "caudal": 25.23, "timestamp": "2026-02-19T05:15:22Z"}, {"nivel": 1.12, "caudal": 25.46, "timestamp": "2026-02-19T05:30:33Z"}, {"nivel": 1.1, "caudal": 24.77, "timestamp": "2026-02-19T05:45:28Z"}, {"nivel": 1.1, "caudal": 24.66, "timestamp": "2026-02-19T06:00:39Z"}, {"nivel": 1.13, "caudal": 26.1, "timestamp": "2026-02-19T06:15:24Z"}, {"nivel": 1.11, "caudal": 25.36, "timestamp": "2026-02-19T06:16:46Z"}, {"nivel": 1.12, "caudal": 25.79, "timestamp": "2026-02-19T06:30:33Z"}]